{"nodes":[{"id":0,"name":"vmCar","type":"VMHost","model":{"disk":"20","cpu":"2","ram":"1024"}},{"id":1,"name":"webdk","type":"DockerContainer","model":{"volumes":[{}],"DockerContainerPorts":[{"container":80,"host":80}],"image":"cloudopting/centosbase:6.6","logtype":"apache","entrypoint":"\"/root/start.sh\""}},{"id":2,"name":"webserver","type":"Apache","model":{"default_mods":true,"default_vhost":false,"portsExpose":[{"port":80}],"mpm_module":"prefork","servername":"fqdn"}},{"id":3,"name":"sitevh","type":"ApacheVirtualHost","model":{"proxy_preserve_host":false,"vhost_name":"*","default_vhost":false,"ssl":false,"port":80,"docroot":"/var/www/wcic","servername":"%%USERINPUT%%"}},{"id":4,"name":"remirepo","type":"Package","model":{"provider":"rpm","source":"http://rpms.remirepo.net/enterprise/remi-release-6.rpm","package_name":"remi-release"}},{"id":5,"name":"phpmod","type":"ApacheModule","model":{"module":"php"}},{"id":6,"name":"sitearchive","type":"Remotefile","model":{"unzip":true,"require":"Class['apache']","target":"/var/www/wcic","destination":"/tmp","extension":"zip","archive":"site","archive_user":"apache","source":"%%SERVURL site.zip%%"}},{"id":7,"name":"phppkg","type":"Package","model":{"package_name":"php","require":"Package['remi-release']","install_options":"[{'--enablerepo'=> 'remi-php56'},]","provider":"yum"}}],"edges":[{"id":"e0","source":0,"target":1,"type":"hostedOn"},{"id":"e1","source":1,"target":2,"type":"hostedOn"},{"id":"e2","source":2,"target":3,"type":"hostedOn"},{"id":"e3","source":1,"target":4,"type":"hostedOn"},{"id":"e4","source":2,"target":5,"type":"hostedOn"},{"id":"e5","source":2,"target":6,"type":"hostedOn"},{"id":"e6","source":1,"target":7,"type":"hostedOn"}],"serviceName":"wcic"}